survey_dud_detector/__init__.py
survey_dud_detector/dud_detector.py
survey_dud_detector-0.2.dist-info/LICENSE.txt
survey_dud_detector-0.2.dist-info/METADATA
survey_dud_detector-0.2.dist-info/WHEEL
survey_dud_detector-0.2.dist-info/top_level.txt
survey_dud_detector-0.2.dist-info/RECORD
