Metadata-Version: 2.1
Name: survey-dud-detector
Version: 0.2
Summary: Automatically detect bad responses in survey responses
Home-page: https://github.com/rethinkpriorities/survey_dud_detector
Author: Peter Hurford
Author-email: peter@peterhurford.com
License: UNKNOWN
Platform: UNKNOWN
Classifier: Development Status :: 3 - Alpha
Classifier: Programming Language :: Python :: 3
Classifier: License :: OSI Approved :: MIT License
Classifier: Operating System :: OS Independent
